py_unpack_sourcemap/__init__.py
py_unpack_sourcemap/__main__.py
py_unpack_sourcemap/_exceptions.py
py_unpack_sourcemap/_logging.py
py_unpack_sourcemap/_main.py
py_unpack_sourcemap/py.typed
py_unpack_sourcemap-1.0.1.dist-info/METADATA
py_unpack_sourcemap-1.0.1.dist-info/WHEEL
py_unpack_sourcemap-1.0.1.dist-info/RECORD
