Metadata-Version: 2.1
Name: py_unpack_sourcemap
Version: 1.0.1
Summary: Unpack JavaScript source maps into source files
Home-page: https://github.com/lonelyteapot/py_unpack_sourcemap
License: MIT
Keywords: sourcemaps
Author: Dmitry Semenov
Author-email: lonelyteapot@gmail.com
Requires-Python: >=3.10,<4.0
Classifier: Development Status :: 4 - Beta
Classifier: Environment :: Console
Classifier: Intended Audience :: Developers
Classifier: License :: OSI Approved :: MIT License
Classifier: Programming Language :: JavaScript
Classifier: Programming Language :: Python :: 3
Classifier: Programming Language :: Python :: 3.10
Classifier: Programming Language :: Python :: 3.11
Classifier: Topic :: File Formats :: JSON
Classifier: Topic :: Software Development :: Code Generators
Classifier: Typing :: Typed
Project-URL: Bug Tracker, https://github.com/lonelyteapot/py_unpack_sourcemap/issues
Project-URL: Repository, https://github.com/lonelyteapot/py_unpack_sourcemap
